COPYRIGHT
MANIFEST.in
Makefile
README
setup.py
test/__init__.py
test/__init__.pyc
test/test_simple.py
test/test_simple.pyc
tiddlywebplugins/__init__.py
tiddlywebplugins/magicuser.py
tiddlywebplugins.magicuser.egg-info/PKG-INFO
tiddlywebplugins.magicuser.egg-info/SOURCES.txt
tiddlywebplugins.magicuser.egg-info/dependency_links.txt
tiddlywebplugins.magicuser.egg-info/namespace_packages.txt
tiddlywebplugins.magicuser.egg-info/not-zip-safe
tiddlywebplugins.magicuser.egg-info/requires.txt
tiddlywebplugins.magicuser.egg-info/top_level.txt