Metadata-Version: 1.0
Name: tiddlywebplugins.magicuser
Version: 0.5
Summary: "magically" extend tiddlyweb user capabilities
Home-page: http://pypi.python.org/pypi/tiddlywebplugins.magicuser
Author: Chris Dent
Author-email: cdent@peermore.com
License: BSD
Platform: Posix; MacOS X; Windows
